cdc_upscaler/__init__.py
cdc_upscaler/device.py
cdc_upscaler/functional.py
cdc_upscaler/upscale.py
cdc_upscaler/config/__init__.py
cdc_upscaler/config/meta.py
cdc_upscaler-0.2.0.dist-info/LICENSE
cdc_upscaler-0.2.0.dist-info/METADATA
cdc_upscaler-0.2.0.dist-info/WHEEL
cdc_upscaler-0.2.0.dist-info/top_level.txt
cdc_upscaler-0.2.0.dist-info/RECORD
