Metadata-Version: 2.1
Name: cdc-upscaler
Version: 0.2.0
Summary: Image upscaler for anime.
Home-page: https://github.com/narugo1992/cdc_upscaler
Author: narugo1992
Author-email: narugo@126.com
License: Apache License, Version 2.0
Keywords: Image upscaler for anime.
Classifier: Development Status :: 5 - Production/Stable
Classifier: Intended Audience :: Developers
Classifier: License :: OSI Approved :: Apache Software License
Classifier: Programming Language :: Python
Classifier: Programming Language :: Python :: 3
Classifier: Programming Language :: Python :: 3.7
Classifier: Programming Language :: Python :: 3.8
Classifier: Programming Language :: Python :: 3.9
Classifier: Programming Language :: Python :: 3.10
Requires-Python: >=3.7
License-File: LICENSE
Requires-Dist: pillow
Requires-Dist: numpy
Requires-Dist: huggingface-hub
Requires-Dist: hbutils >=0.8.0
Requires-Dist: tqdm
Provides-Extra: test
Requires-Dist: coverage >=5 ; extra == 'test'
Requires-Dist: mock >=4.0.3 ; extra == 'test'
Requires-Dist: flake8 ~=3.5 ; extra == 'test'
Requires-Dist: testfixtures >=6.18.5 ; extra == 'test'
Requires-Dist: pytest ~=6.2.5 ; extra == 'test'
Requires-Dist: pytest-cov ~=3.0.0 ; extra == 'test'
Requires-Dist: pytest-mock ~=3.6.1 ; extra == 'test'
Requires-Dist: pytest-xdist >=1.34.0 ; extra == 'test'
Requires-Dist: pytest-rerunfailures ~=10.2 ; extra == 'test'
Requires-Dist: pytest-timeout ~=2.0.2 ; extra == 'test'
Requires-Dist: pytest-benchmark ~=3.4.0 ; extra == 'test'
Requires-Dist: easydict <2,>=1.7 ; extra == 'test'
Requires-Dist: testtools >=2 ; extra == 'test'
Requires-Dist: pytest-image-diff ; extra == 'test'
Requires-Dist: torch ; extra == 'test'
Requires-Dist: hbutils >=0.7 ; extra == 'test'
Provides-Extra: tools
Requires-Dist: torch ; extra == 'tools'
Requires-Dist: onnx ; extra == 'tools'
Requires-Dist: onnxoptimizer ; extra == 'tools'
Requires-Dist: onnxsim ; extra == 'tools'
Requires-Dist: click >=7 ; extra == 'tools'
Requires-Dist: hbutils >=0.7 ; extra == 'tools'
Requires-Dist: tqdm ; extra == 'tools'
